{
  "ams": {
    "color": {
      "background": {
        "canvas": { "value": "#ffffff" },
        "opening": { "value": "#ffffff" }
      },
      "feedback": {
        "error": {
          "default": { "value": "#ec0000" }
        },
        "info": {
          "default": { "value": "#009de6" }
        },
        "success": {
          "default": { "value": "#00a03c" }
        },
        "warning": {
          "default": { "value": "#ff9100" }
        }
      },
      "highlight": {
        "azure": {
          "default": { "value": "#009de6" }
        },
        "green": {
          "default": { "value": "#00a03c" }
        },
        "lime": {
          "default": { "value": "#bed200" }
        },
        "magenta": {
          "default": { "value": "#e50082" }
        },
        "orange": {
          "default": { "value": "#ff9100" }
        },
        "purple": {
          "default": { "value": "#a00078" }
        },
        "yellow": {
          "default": { "value": "#ffe600" }
        }
      },
      "interactive": {
        "default": { "value": "#004699" },
        "hover": { "value": "#003677" },
        "contrast": {
          "default": { "value": "#000000" }
        },
        "disabled": {
          "default": { "value": "#767676" }
        },
        "invalid": {
          "default": { "value": "#ec0000" },
          "hover": { "value": "#b70000" }
        },
        "inverse": {
          "default": { "value": "#ffffff" }
        },
        "secondary": {
          "default": { "value": "#181818" }
        }
      },
      "separator": {
        "default": { "value": "#d1d1d1" }
      },
      "text": {
        "default": { "value": "#181818" },
        "secondary": { "value": "#767676" },
        "inverse": { "value": "#ffffff" }
      }
    }
  }
}
